loganalysispackage/__init__.py
loganalysispackage/average.py
loganalysispackage/classify.py
loganalysispackage/configreader.py
loganalysispackage/datasource.py
loganalysispackage/elasticsearchconn.py
loganalysispackage/loganalysis.py
loganalysispackage/model.py
loganalysispackage/mongoconn.py
loganalysispackage/prediction.py
loganalysispackage-0.6.dist-info/LICENSE
loganalysispackage-0.6.dist-info/METADATA
loganalysispackage-0.6.dist-info/WHEEL
loganalysispackage-0.6.dist-info/top_level.txt
loganalysispackage-0.6.dist-info/RECORD
