Metadata-Version: 2.1
Name: loganalysispackage
Version: 0.6
Summary: loganalysispackage
Home-page: https://github.com/shinjiniray/loganalysispackage
Author: Shinjini Ray
Author-email: shinjini.ray@gmail.com
License: MIT
Download-URL: https://pypi.org/project/loganalysispackage
Keywords: log,analysis,neuralnetwork
Platform: UNKNOWN
Requires-Dist: pymongo
Requires-Dist: dnspython
Requires-Dist: elasticsearch
Requires-Dist: numpy (==1.18.5)
Requires-Dist: sklearn
Requires-Dist: tensorflow
Requires-Dist: matplotlib
